{
  "type" : "urn:xiot-spec:device:switch:0000a003:roome:v2:1",
  "description" : "Switch",
  "services" : [ {
    "iid" : 1,
    "type" : "urn:xiot-spec:service:device-information:00007801:roome:v2:1",
    "description" : "Device Information",
    "properties" : [ {
      "iid" : 1,
      "type" : "urn:xiot-spec:property:manufacturer:00000001:roome:v2:1",
      "description" : "Device Manufacturer",
      "format" : "string",
      "access" : [ "read" ]
    }, {
      "iid" : 2,
      "type" : "urn:xiot-spec:property:model:00000002:roome:v2:1",
      "description" : "Device Model",
      "format" : "string",
      "access" : [ "read" ]
    }, {
      "iid" : 3,
      "type" : "urn:xiot-spec:property:serial-number:00000003:roome:v2:1",
      "description" : "Device Serial Number",
      "format" : "string",
      "access" : [ "read" ]
    }, {
      "iid" : 4,
      "type" : "urn:xiot-spec:property:name:00000004:roome:v2:1",
      "description" : "Device Name",
      "format" : "string",
      "access" : [ "read" ]
    }, {
      "iid" : 5,
      "type" : "urn:xiot-spec:property:firmware-revision:00000005:roome:v2:1",
      "description" : "Current Firmware Version",
      "format" : "string",
      "access" : [ "read" ]
    } ]
  }, {
    "iid" : 2,
    "type" : "urn:xiot-spec:service:switch:0000780c:roome:v2:1",
    "description" : "Left Switch Service",
    "properties" : [ {
      "iid" : 1,
      "type" : "urn:xiot-spec:property:on:00000006:roome:v2:1",
      "description" : "Switch Status",
      "format" : "bool",
      "access" : [ "read", "write", "notify" ]
    }, {
      "iid" : 2,
      "type" : "urn:xiot-spec:property:name:00000004:roome:v2:1",
      "description" : "Name of Service",
      "format" : "string",
      "access" : [ "read" ]
    } ]
  }, {
    "iid" : 3,
    "type" : "urn:xiot-spec:service:switch:0000780c:roome:v2:1",
    "description" : "Middle Switch Service",
    "properties" : [ {
      "iid" : 1,
      "type" : "urn:xiot-spec:property:on:00000006:roome:v2:1",
      "description" : "Switch Status",
      "format" : "bool",
      "access" : [ "read", "write", "notify" ]
    }, {
      "iid" : 2,
      "type" : "urn:xiot-spec:property:name:00000004:roome:v2:1",
      "description" : "Name of Service",
      "format" : "string",
      "access" : [ "read" ]
    } ]
  }, {
    "iid" : 4,
    "type" : "urn:xiot-spec:service:switch:0000780c:roome:v2:1",
    "description" : "Right Switch Service",
    "properties" : [ {
      "iid" : 1,
      "type" : "urn:xiot-spec:property:on:00000006:roome:v2:1",
      "description" : "Switch Status",
      "format" : "bool",
      "access" : [ "read", "write", "notify" ]
    }, {
      "iid" : 2,
      "type" : "urn:xiot-spec:property:name:00000004:roome:v2:1",
      "description" : "Name of Service",
      "format" : "string",
      "access" : [ "read" ]
    } ]
  }, {
    "iid" : 5,
    "type" : "urn:xiot-spec:service:battery:00007805:roome:v2:1",
    "description" : "Battery",
    "properties" : [ {
      "iid" : 1,
      "type" : "urn:xiot-spec:property:battery-level:00000014:roome:v2:1",
      "description" : "Battery Level",
      "format" : "uint8",
      "access" : [ "read", "notify" ],
      "value-list" : [ {
        "value" : 0,
        "description" : "NONE"
      }, {
        "value" : 1,
        "description" : "LOW"
      }, {
        "value" : 2,
        "description" : "NORMAL"
      }, {
        "value" : 3,
        "description" : "FULL"
      } ]
    } ]
  } ]
}